{
  "users": [
    {
      "email": "abc@mail.com",
      "password": "$2a$10$LOZxtPMTZu5UI.ZY2nvhVeTrN7rWicWRCPFQYNDQvQ00sTXgmmwgy",
      "id": 1
    },
    {
      "email": "hello@mail.com",
      "password": "$2a$10$qoRPfMTK359Rp0UKkebLJeNGlObmxfR9U8OsHe5edae.JCUK.Gwsu",
      "id": 2
    },
    {
      "email": "hi@mail.com",
      "password": "$2a$10$S20oDnuC3bZu7ANPJgcqvusSCv0jc8P621OAQsKc1urH7HcrLLiCS",
      "id": 3
    }
  ],
  "weather_history": [
    {
      "date": "2023-6-14",
      "name": "Rome",
      "weather": "Clear",
      "temp": 17,
      "humidity": 100,
      "wind_speed": 100,
      "feels_like": 17,
      "id": 1
    },
    {
      "date": "2023-6-14",
      "name": "Yangon",
      "weather": "Overcast",
      "temp": 29.8,
      "humidity": 61,
      "wind_speed": 191,
      "feels_like": 32.9,
      "id": 2
    },
    {
      "date": "2023-6-14",
      "name": "Yangon",
      "weather": "Moderate or heavy rain shower",
      "temp": 28.2,
      "humidity": 82,
      "wind_speed": 214,
      "feels_like": 33,
      "id": 3
    },
    {
      "date": "2023-6-14",
      "name": "Rome",
      "weather": "Clear",
      "temp": 17,
      "humidity": 100,
      "wind_speed": 120,
      "feels_like": 17,
      "id": 4
    },
    {
      "date": "2023-6-14",
      "name": "Seoul",
      "weather": "Light rain",
      "temp": 25,
      "humidity": 57,
      "wind_speed": 260,
      "feels_like": 25.1,
      "id": 5
    },
    {
      "date": "2023-6-14",
      "name": "Seoul",
      "weather": "Light rain",
      "temp": 25,
      "humidity": 57,
      "wind_speed": 260,
      "feels_like": 25.1,
      "id": 6
    },
    {
      "date": "2023-6-14",
      "name": "Mandalay",
      "weather": "Overcast",
      "temp": 30.4,
      "humidity": 59,
      "wind_speed": 190,
      "feels_like": 33.7,
      "id": 7
    },
    {
      "date": "2023-6-14",
      "name": "Yangon",
      "weather": "Moderate rain",
      "temp": 25,
      "humidity": 100,
      "wind_speed": 310,
      "feels_like": 26.9,
      "id": 8
    },
    {
      "date": "2023-6-14",
      "name": "Haganggol",
      "weather": "Clear",
      "temp": 20,
      "humidity": 83,
      "wind_speed": 340,
      "feels_like": 20,
      "id": 9
    },
    {
      "date": "2023-6-14",
      "name": "Beijing",
      "weather": "Clear",
      "temp": 26,
      "humidity": 54,
      "wind_speed": 90,
      "feels_like": 25.7,
      "id": 10
    },
    {
      "date": "2023-6-14",
      "name": "Yangon",
      "weather": "Moderate rain",
      "temp": 25,
      "humidity": 100,
      "wind_speed": 310,
      "feels_like": 26.9,
      "id": 11
    }
  ]
}